setup.py
optimalgo/AST_Analyzer.py
optimalgo/CodeAnalysis.py
optimalgo/Data_Match.py
optimalgo/Fragment.py
optimalgo/FragmentExecutor.py
optimalgo/FragmentGenerator.py
optimalgo/Node.py
optimalgo/__init__.py
optimalgo.egg-info/PKG-INFO
optimalgo.egg-info/SOURCES.txt
optimalgo.egg-info/dependency_links.txt
optimalgo.egg-info/requires.txt
optimalgo.egg-info/top_level.txt