Metadata-Version: 1.0
Name: optimalgo
Version: 0.3
Summary: Python Code Optimization & Recommendation
Home-page: UNKNOWN
Author: UNKNOWN
Author-email: UNKNOWN
License: UNKNOWN
Platform: UNKNOWN
